README.md
setup.cfg
setup.py
ems/__init__.py
ems/run.py
ems/utils.py
ems/algorithms/__init__.py
ems/algorithms/ambulance.py
ems/algorithms/base.py
ems/algorithms/hospital.py
ems/analysis/__init__.py
ems/analysis/coverage.py
ems/analysis/metric.py
ems/analysis/record.py
ems/datasets/__init__.py
ems/datasets/ambulance.py
ems/datasets/base.py
ems/datasets/case.py
ems/datasets/demand.py
ems/datasets/hospital.py
ems/datasets/location.py
ems/datasets/scenario.py
ems/datasets/times.py
ems/generators/__init__.py
ems/generators/duration.py
ems/generators/event.py
ems/generators/location.py
ems/generators/priority.py
ems/models/__init__.py
ems/models/ambulance.py
ems/models/capability.py
ems/models/case.py
ems/models/event.py
ems/scenarios/__init__.py
ems/scenarios/controller.py
ems/scenarios/scenario.py
ems/simulators/__init__.py
ems/simulators/simulator.py
ems/triggers/__init__.py
ems/triggers/trigger.py
ems_simulator.egg-info/PKG-INFO
ems_simulator.egg-info/SOURCES.txt
ems_simulator.egg-info/dependency_links.txt
ems_simulator.egg-info/requires.txt
ems_simulator.egg-info/top_level.txt